DockerBuildSystem/DockerComposeTools.py
DockerBuildSystem/DockerImageTools.py
DockerBuildSystem/DockerSwarmTools.py
DockerBuildSystem/TerminalTools.py
DockerBuildSystem/VersionTools.py
DockerBuildSystem/YamlTools.py
DockerBuildSystem/__init__.py
DockerBuildSystem-1.1.64.dist-info/LICENSE
DockerBuildSystem-1.1.64.dist-info/METADATA
DockerBuildSystem-1.1.64.dist-info/WHEEL
DockerBuildSystem-1.1.64.dist-info/top_level.txt
DockerBuildSystem-1.1.64.dist-info/RECORD
